elasticdl/Makefile
elasticdl/__init__.py
elasticdl/requirements.txt
elasticdl/docker/Dockerfile
elasticdl/docker/Dockerfile.ci
elasticdl/docker/bashrc
elasticdl/go/bin/elasticdl_ps
elasticdl/go/pkg/kernel/capi/kernel_api.cc
elasticdl/go/pkg/kernel/capi/kernel_api.h
elasticdl/go/pkg/kernel/capi/libkernel_api.a
elasticdl/go/pkg/kernel/capi/libkernel_api.o
elasticdl/proto/__init__.py
elasticdl/proto/elasticdl.proto
elasticdl/proto/elasticdl_pb2.py
elasticdl/proto/elasticdl_pb2_grpc.py
elasticdl/python/__init__.py
elasticdl/python/collective_ops/__init__.py
elasticdl/python/collective_ops/communicator.py
elasticdl/python/common/__init__.py
elasticdl/python/common/args.py
elasticdl/python/common/constants.py
elasticdl/python/common/dtypes.py
elasticdl/python/common/evaluation_utils.py
elasticdl/python/common/file_utils.py
elasticdl/python/common/grpc_utils.py
elasticdl/python/common/hash_utils.py
elasticdl/python/common/k8s_client.py
elasticdl/python/common/k8s_job_monitor.py
elasticdl/python/common/k8s_tensorboard_client.py
elasticdl/python/common/log_utils.py
elasticdl/python/common/model_handler.py
elasticdl/python/common/model_utils.py
elasticdl/python/common/save_utils.py
elasticdl/python/common/tensor_utils.py
elasticdl/python/common/timing_utils.py
elasticdl/python/data/__init__.py
elasticdl/python/data/odps_io.py
elasticdl/python/data/odps_recordio_conversion_utils.py
elasticdl/python/data/reader/__init__.py
elasticdl/python/data/reader/csv_reader.py
elasticdl/python/data/reader/data_reader.py
elasticdl/python/data/reader/data_reader_factory.py
elasticdl/python/data/reader/odps_reader.py
elasticdl/python/data/reader/recordio_reader.py
elasticdl/python/data/recordio_gen/__init__.py
elasticdl/python/data/recordio_gen/census_recordio_gen.py
elasticdl/python/data/recordio_gen/frappe_recordio_gen.py
elasticdl/python/data/recordio_gen/heart_recordio_gen.py
elasticdl/python/data/recordio_gen/image_label.py
elasticdl-0.2.0rc3.dist-info/DESCRIPTION.rst
elasticdl-0.2.0rc3.dist-info/METADATA
elasticdl-0.2.0rc3.dist-info/RECORD
elasticdl-0.2.0rc3.dist-info/WHEEL
elasticdl-0.2.0rc3.dist-info/metadata.json
elasticdl-0.2.0rc3.dist-info/top_level.txt
