Metadata-Version: 2.0
Name: elasticdl
Version: 0.2.0rc3
Summary: A Kubernetes-native Deep Learning Framework
Home-page: https://elasticdl.org
Author: Ant Financial
License: UNKNOWN
Platform: UNKNOWN
Requires-Python: >=3.5
Provides-Extra: develop
Requires-Dist: grpcio-tools (==1.29.0)
Requires-Dist: kubernetes (==10.1.0)
Requires-Dist: docker (==4.2.1)
Requires-Dist: pyrecordio (>=0.0.6)
Requires-Dist: Cython
Requires-Dist: odps
Requires-Dist: tensorflow (==2.1.0)
Requires-Dist: deepctr
Requires-Dist: elasticdl-client
Requires-Dist: elasticdl-preprocessing
Provides-Extra: develop
Requires-Dist: pytest; extra == 'develop'
Requires-Dist: pytest-cov; extra == 'develop'
Requires-Dist: mock; extra == 'develop'
Requires-Dist: Pillow; extra == 'develop'
Requires-Dist: pre-commit; extra == 'develop'
Requires-Dist: pandas; extra == 'develop'
Requires-Dist: sklearn; extra == 'develop'
Requires-Dist: yamllint; extra == 'develop'
